cognixis/__init__.py
cognixis/train.py
cognixis-0.1.9.dist-info/METADATA
cognixis-0.1.9.dist-info/WHEEL
cognixis-0.1.9.dist-info/top_level.txt
cognixis-0.1.9.dist-info/RECORD
