Metadata-Version: 2.1
Name: cognixis
Version: 0.1.9
Summary: A PyTorch training loop utility
Home-page: https://github.com/sidhu2690/CogniXis
Author: Sidh2690
Author-email: sidhu2690@gmail.com
License: UNKNOWN
Platform: UNKNOWN
Classifier: Programming Language :: Python :: 3
Classifier: License :: OSI Approved :: MIT License
Classifier: Operating System :: OS Independent
Requires-Python: >=3.6
Requires-Dist: numpy
Requires-Dist: torch (>=1.0)
Requires-Dist: torchinfo (>=1.7)
